Metadata-Version: 1.0
Name: physicist
Version: 0.0.1
Summary: Computational physics package
Home-page: https://github.com/jay-woo/Computational-Physics
Author: Jay Woo
Author-email: jay.woo456456@gmail.com
License: MIT License
